{
	"animations": [
		{
			"loop": false,
			"offsets": [
				112,
				187
			],
			"anim": "singLEFT",
			"fps": 36,
			"name": "Hank Left Note",
			"indices": []
		},
		{
			"loop": false,
			"offsets": [
				-182,
				171
			],
			"anim": "singDOWN",
			"fps": 36,
			"name": "Hank Down Note",
			"indices": []
		},
		{
			"loop": false,
			"offsets": [
				-206,
				173
			],
			"anim": "singUP",
			"fps": 36,
			"name": "Hank Up note",
			"indices": []
		},
		{
			"loop": false,
			"offsets": [
				-124,
				179
			],
			"anim": "singRIGHT",
			"fps": 36,
			"name": "Hank right note",
			"indices": []
		},
		{
			"offsets": [
				-164,
				187
			],
			"loop": false,
			"fps": 36,
			"anim": "shootLEFT",
			"indices": [],
			"name": "Hank Left Shoot"
		},
		{
			"offsets": [
				-240,
				179
			],
			"loop": false,
			"fps": 36,
			"anim": "shootRIGHT",
			"indices": [],
			"name": "Hank right shoot"
		},
		{
			"offsets": [
				-182,
				170
			],
			"loop": false,
			"fps": 36,
			"anim": "shootDOWN",
			"indices": [],
			"name": "Hank Down Shoot"
		},
		{
			"offsets": [
				-206,
				174
			],
			"loop": false,
			"fps": 36,
			"anim": "shootUP",
			"indices": [],
			"name": "Hank Up shoot"
		},
		{
			"loop": false,
			"offsets": [
				-215,
				171
			],
			"anim": "idle",
			"fps": 36,
			"name": "Hank Idle",
			"indices": []
		},
		{
			"offsets": [
				-215,
				171
			],
			"loop": true,
			"fps": 36,
			"anim": "idle-loop",
			"indices": [
				9,
				10,
				11,
				12,
				13,
				14
			],
			"name": "Hank Idle"
		},
		{
			"loop": false,
			"offsets": [
				-201,
				170
			],
			"anim": "idle-scared",
			"fps": 36,
			"name": "HankScaredIdle",
			"indices": []
		},
		{
			"offsets": [
				-201,
				170
			],
			"loop": true,
			"fps": 36,
			"anim": "idle-scared-loop",
			"indices": [
				8,
				9,
				10,
				11,
				12,
				13
			],
			"name": "HankScaredIdle"
		},
		{
			"loop": true,
			"offsets": [
				-206,
				173
			],
			"anim": "singUP-loop",
			"fps": 36,
			"name": "Hank Up note",
			"indices": [
				7,
				8,
				9,
				10,
				11,
				12,
				13
			]
		},
		{
			"loop": true,
			"offsets": [
				112,
				187
			],
			"anim": "singLEFT-loop",
			"fps": 36,
			"name": "Hank Left Note",
			"indices": [
				6,
				7,
				8,
				9,
				10,
				11,
				12,
				13
			]
		},
		{
			"loop": true,
			"offsets": [
				-182,
				171
			],
			"anim": "singDOWN-loop",
			"fps": 36,
			"name": "Hank Down Note",
			"indices": [
				7,
				8,
				9,
				10,
				11,
				12,
				13
			]
		},
		{
			"loop": true,
			"offsets": [
				-124,
				179
			],
			"anim": "singRIGHT-loop",
			"fps": 36,
			"name": "Hank right note",
			"indices": [
				2,
				3,
				4,
				5,
				6,
				7,
				8
			]
		},
		{
			"loop": false,
			"offsets": [
				-207,
				86
			],
			"anim": "getReady",
			"fps": 36,
			"name": "HankGetReady",
			"indices": []
		},
		{
			"offsets": [
				-207,
				86
			],
			"loop": true,
			"fps": 36,
			"anim": "getReady-loop",
			"indices": [
				16,
				17,
				18,
				19,
				20,
				21,
				22,
				23,
				24
			],
			"name": "HankGetReady"
		},
		{
			"offsets": [
				-50,
				138
			],
			"loop": false,
			"fps": 36,
			"anim": "hey",
			"indices": [],
			"name": "hanktaunt"
		},
		{
			"offsets": [
				-110,
				494
			],
			"loop": false,
			"fps": 24,
			"anim": "scaredShoot",
			"indices": [],
			"name": "HankScaredShootsTiky"
		},
		{
			"loop": true,
			"offsets": [
				-110,
				494
			],
			"anim": "scaredShoot-loop",
			"fps": 24,
			"name": "HankScaredShootsTiky",
			"indices": [
				9,
				10,
				11,
				12
			]
		},
		{
			"offsets": [
				-50,
				138
			],
			"loop": true,
			"fps": 36,
			"anim": "hey-loop",
			"indices": [
				8,
				9,
				10,
				11,
				12,
				13,
				14,
				15
			],
			"name": "hanktaunt"
		},
		{
			"offsets": [
				-137,
				180
			],
			"indices": [],
			"fps": 24,
			"anim": "singRIGHT-alt",
			"loop": false,
			"name": "Hank screamright"
		},
		{
			"offsets": [
				-137,
				180
			],
			"indices": [
				30,
				31,
				32,
				33,
				34,
				35,
				36
			],
			"fps": 24,
			"anim": "singRIGHT-alt-loop",
			"loop": true,
			"name": "Hank screamright"
		}
	],
	"no_antialiasing": false,
	"image": "characters/HankAssets",
	"position": [
		-250,
		360
	],
	"healthicon": "hank",
	"flip_x": false,
	"healthbar_colors": [
		255,
		0,
		40
	],
	"camera_position": [
		220,
		-150
	],
	"sing_duration": 2.6,
	"scale": 1
}