{
	"animations": [
		{
			"offsets": [
				0,
				0
			],
			"loop": false,
			"fps": 24,
			"anim": "danceRight",
			"indices": [],
			"name": "trickyidle"
		},
		{
			"loop": false,
			"offsets": [
				0,
				0
			],
			"anim": "danceLeft",
			"fps": 24,
			"name": "trickyidle",
			"indices": []
		},
		{
			"offsets": [
				291,
				613
			],
			"loop": false,
			"fps": 36,
			"anim": "Scream",
			"indices": [
				8,
				9,
				10,
				11,
				12,
				13,
				14,
				15,
				16,
				17,
				18,
				19,
				20,
				21,
				22,
				23,
				24,
				25,
				26,
				27,
				28,
				29,
				30,
				31,
				32,
				33,
				34,
				35,
				36,
				37,
				38
			],
			"name": "trickyentrance"
		},
		{
			"offsets": [
				89,
				16
			],
			"loop": false,
			"fps": 36,
			"anim": "singDOWN",
			"indices": [],
			"name": "trickydwon"
		},
		{
			"offsets": [
				-16,
				66
			],
			"loop": false,
			"fps": 36,
			"anim": "singUP",
			"indices": [],
			"name": "trickyup"
		},
		{
			"offsets": [
				110,
				33
			],
			"loop": false,
			"fps": 36,
			"anim": "singLEFT",
			"indices": [],
			"name": "trickyileft"
		},
		{
			"offsets": [
				145,
				-26
			],
			"loop": false,
			"fps": 36,
			"anim": "singRIGHT",
			"indices": [],
			"name": "trickyright"
		},
		{
			"offsets": [
				-11,
				23
			],
			"loop": false,
			"fps": 24,
			"anim": "Turn",
			"indices": [],
			"name": "trickyturning"
		},
		{
			"offsets": [
				9,
				250
			],
			"loop": true,
			"fps": 24,
			"anim": "Fall",
			"indices": [],
			"name": "tikygetsshot"
		},
		{
			"loop": false,
			"offsets": [
				291,
				613
			],
			"anim": "Enter",
			"fps": 24,
			"name": "trickyentrance",
			"indices": [
				0,
				1,
				2,
				8,
				9,
				35,
				36,
				37,
				38
			]
		}
	],
	"no_antialiasing": false,
	"image": "characters/TrickyAssets",
	"position": [
		90,
		-147
	],
	"healthicon": "hank",
	"flip_x": false,
	"healthbar_colors": [
		22,
		22,
		44
	],
	"camera_position": [
		0,
		400
	],
	"sing_duration": 4,
	"scale": 1.05
}